{"schools":[{"schoolName":"Unaffiliated","depts":[{"deptCode":"UCDC","courses":[{"courseNumber":"180","courseTitle":"PRESIDENCY","sections":[{"enrolled":"1","meetings":[{"bldg":"TBA ","days":"","time":"TBA"}]}]},{"courseNumber":"170","courseTitle":"WASH DC INTERNSHIP","sections":[{"enrolled":"23","meetings":[{"bldg":"TBA ","days":"","time":"TBA"}]}]},{"courseNumber":"180","courseTitle":"CONGRESS","sections":[{"enrolled":"3","meetings":[{"bldg":"TBA ","days":"","time":"TBA"}]}]},{"courseNumber":"180","courseTitle":"GENERAL RESEARCH","sections":[{"enrolled":"1","meetings":[{"bldg":"TBA ","days":"","time":"TBA"}]}]},{"courseNumber":"180","courseTitle":"INTERNATIONL POLICY","sections":[{"enrolled":"2","meetings":[{"bldg":"TBA ","days":"","time":"TBA"}]}]},{"courseNumber":"180","courseTitle":"WASHINGTON FOCUS","sections":[{"enrolled":"0","meetings":[{"bldg":"TBA ","days":"","time":"TBA"}]}]},{"courseNumber":"180","courseTitle":"WASHINGTON MEDIA","sections":[{"enrolled":"5","meetings":[{"bldg":"TBA ","days":"","time":"TBA"}]}]},{"courseNumber":"180","courseTitle":"THE SUPREME COURT","sections":[{"enrolled":"11","meetings":[{"bldg":"TBA ","days":"","time":"TBA"}]}]},{"courseNumber":"180","courseTitle":"INTERNATL DEVELOP","sections":[{"enrolled":"0","meetings":[{"bldg":"TBA ","days":"","time":"TBA"}]}]},{"courseNumber":"190","courseTitle":"WASH DC ELECTIVE","sections":[{"enrolled":"6","meetings":[{"bldg":"TBA ","days":"","time":"TBA"}]}]}]}]}]}