{"schools":[{"schoolName":"Paul Merage School of Business","depts":[{"deptCode":"INNO","courses":[{"courseNumber":"211","courseTitle":"NEW VENTURE COMP","sections":[{"enrolled":"41","meetings":[{"bldg":"SB1 2321","days":"Tu","time":" 8:00-10:50 "}]}]},{"courseNumber":"214","courseTitle":"IE:ENTREPRENEURSHIP","sections":[{"enrolled":"41","meetings":[{"bldg":"OFF CAMPUS","days":"Tu","time":" 2:30- 5:20p"}]}]},{"courseNumber":"218","courseTitle":"IE:VENTURE CAPITAL","sections":[{"enrolled":"41","meetings":[{"bldg":"SB1 2321","days":"W","time":"12:30- 3:20p"}]}]},{"courseNumber":"292","courseTitle":"IE:BUSINESS LAW","sections":[{"enrolled":"41","meetings":[{"bldg":"SB1 2321","days":"W","time":"12:30- 3:20p"}]}]},{"courseNumber":"252D","courseTitle":"IE:NEW PRODUCT DEVI","sections":[{"enrolled":"26","meetings":[{"bldg":"SB1 2321","days":"Th","time":"12:30- 3:20p"}]}]},{"courseNumber":"257","courseTitle":"IE:MKTG ON INTERNET","sections":[{"enrolled":"60","meetings":[{"bldg":"ON LINE","days":"","time":"TBA"}]}]}]}]}]}